{
    "id": "10402617",
    "canon": "Gundam Build Fighters/\u30ac\u30f3\u30c0\u30e0\u30d3\u30eb\u30c9\u30d5\u30a1\u30a4\u30bf\u30fc\u30ba",
    "author_id": 50111,
    "title": "too many to count",
    "lang": "English",
    "published": 1401740597,
    "genres": [
        "Family",
        "Friendship"
    ],
    "canon_type": [
        "Anime/Manga"
    ],
    "rated": "Fiction  K",
    "num_words": 4019,
    "num_reviews": 9,
    "num_favs": 20,
    "num_follows": 8,
    "status": "Complete"
}