{
    "id": "2353170",
    "canon": "Battlestar Galactica: 2003",
    "author_id": 82278,
    "title": "A Time to Heal",
    "lang": "English",
    "published": 1113628939,
    "genres": [
        "K. Thrace",
        "Starbuck, K. Agathon",
        "Helo"
    ],
    "canon_type": [
        "TV Shows"
    ],
    "updated": 1114143408,
    "rated": "Fiction  T",
    "num_chapters": 2,
    "num_words": 5699,
    "num_reviews": 11,
    "num_favs": 1,
    "num_follows": 1,
    "status": "Complete"
}