{
    "id": "4014624",
    "canon": "Dragon Ball Z",
    "author_id": 187709,
    "title": "She's Everywhere - Dragonball B V (Bulma and Vegeta)",
    "lang": "English",
    "published": 1200469291,
    "genres": [
        "Romance",
        "Humor"
    ],
    "canon_type": [
        "Anime/Manga"
    ],
    "updated": 1423039311,
    "rated": "Fiction  T",
    "num_chapters": 26,
    "num_words": 34429,
    "num_reviews": 119,
    "num_favs": 180,
    "num_follows": 63,
    "status": "Complete"
}