{
    "id": "626517",
    "canon": "Magic Knight Rayearth/\u9b54\u6cd5\u9a0e\u58eb\u30ec\u30a4\u30a2\u30fc\u30b9",
    "author_id": 112112,
    "title": "New Legend",
    "lang": "English",
    "published": 1014772498,
    "genres": [
        "Romance"
    ],
    "canon_type": [
        "Anime/Manga"
    ],
    "updated": 1069040967,
    "rated": "Fiction  M",
    "num_chapters": 12,
    "num_words": 15193,
    "num_reviews": 28,
    "num_favs": 8,
    "num_follows": 1,
    "status": "Incomplete"
}