{
    "id": "7689271",
    "canon": "ManHua/Chinese Comics/\u6f2b\u753b",
    "author_id": 207279,
    "title": "A Very Merry Infinite Holiday Tale",
    "lang": "English",
    "published": 1325228965,
    "genres": [
        "Friendship",
        "Romance"
    ],
    "canon_type": [
        "Misc"
    ],
    "updated": 1326654456,
    "rated": "Fiction  K+",
    "num_chapters": 2,
    "num_words": 7907,
    "num_reviews": 23,
    "num_favs": 52,
    "num_follows": 15,
    "status": "Complete"
}