{
    "id": "8105902",
    "canon": "Avengers",
    "author_id": 169432,
    "title": "A Neutral Zone Armed With Mistrust And Cynicism",
    "lang": "English",
    "published": 1336740611,
    "genres": [
        "Black Widow",
        "Natasha R., Hulk",
        "Bruce B."
    ],
    "canon_type": [
        "Movies"
    ],
    "updated": 1337115453,
    "rated": "Fiction  K+",
    "num_chapters": 5,
    "num_words": 5230,
    "num_reviews": 71,
    "num_favs": 180,
    "num_follows": 75,
    "status": "Complete"
}