{
    "id": "1820146",
    "canon": "Card Captor Sakura",
    "author_id": 160428,
    "title": "\u00a7 \u2018Finding Myself In Your Eyes\u2019 \u00a7",
    "lang": "English",
    "published": 1082033776,
    "genres": [
        "Romance",
        "Humor"
    ],
    "canon_type": [
        "Anime/Manga"
    ],
    "updated": 1116321770,
    "rated": "Fiction  T",
    "num_chapters": 15,
    "num_words": 155705,
    "num_reviews": 644,
    "num_favs": 210,
    "num_follows": 93,
    "status": "Incomplete"
}