{
    "id": "241234",
    "canon": "Sailor Moon",
    "author_id": 54258,
    "title": "Alone",
    "lang": "English",
    "published": 985939200,
    "genres": [
        "Usagi T.",
        "Serena",
        "Bunny",
        "Sailor Moon, Mamoru C.",
        "Darien S.",
        "Tuxedo Kamen"
    ],
    "canon_type": [
        "Anime/Manga"
    ],
    "rated": "Fiction  K+",
    "num_chapters": 6,
    "num_words": 36238,
    "num_reviews": 49,
    "num_favs": 128,
    "num_follows": 27,
    "status": "Complete"
}