{
    "id": "9529670",
    "canon": "My Little Sister Can't Be This Cute/\u4ffa\u306e\u59b9\u304c\u3053\u3093\u306a\u306b\u53ef\u611b\u3044\u308f\u3051\u304c\u306a\u3044 + Sword Art Online/\u30bd\u30fc\u30c9\u30a2\u30fc\u30c8\u30fb\u30aa\u30f3\u30e9\u30a4\u30f3 Crossover",
    "author_id": 153860,
    "title": "I Cannot Be Stuck In This Game",
    "lang": "English",
    "published": 1374802163,
    "genres": [
        "Romance",
        "Adventure"
    ],
    "updated": 1376630450,
    "rated": "Fiction  T",
    "num_chapters": 5,
    "num_words": 22481,
    "num_reviews": 23,
    "num_favs": 57,
    "num_follows": 63,
    "status": "Incomplete"
}